lab3/lab3_03_piezo/src/lab3_piezo.v
`timescale 1ns/1ps
module lab3_piezo #(
    parameter integer CLK_HZ = 50_000_000,
    parameter integer TONE_HZ = 294
) (
    input  wire clk_50mhz,
    input  wire rst_p,
    output reg  piezo
);
    localparam integer HALF_PERIOD = CLK_HZ / (2 * TONE_HZ);
    localparam integer COUNT_WIDTH = (HALF_PERIOD < 2) ? 1 : $clog2(HALF_PERIOD);
    reg [COUNT_WIDTH-1:0] count;

    always @(posedge clk_50mhz or posedge rst_p) begin
        if (rst_p) begin
            count <= 0;
            piezo <= 0;
        end else if (count == HALF_PERIOD - 1) begin
            count <= 0;
            piezo <= ~piezo;
        end else begin
            count <= count + 1'b1;
        end
    end
endmodule

lab3/report/pre/mod/03_piezo/modified/sim/tb_piezo.sv
`timescale 1ns/1ps
module tb_piezo;
    reg clk_50mhz=0,rst_p=1;
    wire piezo;
    integer cycles,last_cycle=-1,edges=0;
    always #10 clk_50mhz=~clk_50mhz;
    lab3_piezo #(.CLK_HZ(1000),.TONE_HZ(125)) dut(.clk_50mhz(clk_50mhz),.rst_p(rst_p),.piezo(piezo));
    initial begin
      $dumpfile("wave.vcd");$dumpvars(0,tb_piezo);
      repeat(3)@(posedge clk_50mhz);rst_p=0;
      for(cycles=1;cycles<=25;cycles=cycles+1)begin
        @(posedge clk_50mhz);#1;
        if(piezo!==dut.piezo)$fatal(1,"unknown output");
        if(dut.count==0)begin
          if(last_cycle>=0 && cycles-last_cycle!=5)$fatal(1,"half period=%0d",cycles-last_cycle);
          last_cycle=cycles;edges=edges+1;
        end
      end
      if(edges<4)$fatal(1,"too few edges");
      $display("LAB3_PIEZO_PASS edges=%0d",edges);$finish;
    end
    initial begin #5000;$fatal(1,"timeout");end
endmodule

lab3/report/pre/mod/03_piezo/modified/icarus/wave.vcd
$date
	Mon Sep 28 01:18:48 2026
$end
$version
	Icarus Verilog
$end
$timescale
	1ps
$end
$scope module tb_piezo $end
$var wire 1 ! piezo $end
$var reg 1 " clk_50mhz $end
$var reg 1 # rst_p $end
$var integer 32 $ cycles [31:0] $end
$var integer 32 % edges [31:0] $end
$var integer 32 & last_cycle [31:0] $end
$scope module dut $end
$var wire 1 " clk_50mhz $end
$var wire 1 # rst_p $end
$var parameter 32 ' CLK_HZ $end
$var parameter 32 ( COUNT_WIDTH $end
$var parameter 32 ) HALF_PERIOD $end
$var parameter 32 * TONE_HZ $end
$var reg 2 + count [1:0] $end
$var reg 1 ! piezo $end
$upscope $end
$upscope $end
$enddefinitions $end
$comment Show the parameter values. $end
$dumpall
b1111101 *
b100 )
b10 (
b1111101000 '
$end
#0
$dumpvars
bx +
b11111111111111111111111111111111 &
b0 %
bx $
1#
0"
x!
$end
#10000
0!
b0 +
1"
#20000
0"
#30000
1"
#40000
0"
#50000
b1 +
b1 $
0#
1"
#60000
0"
#70000
b10 +
1"
#71000
b10 $
#80000
0"
#90000
b11 +
1"
#91000
b11 $
#100000
0"
#110000
1!
b0 +
1"
#111000
b100 $
b1 %
b11 &
#120000
0"
#130000
b1 +
1"
#131000
b101 $
#140000
0"
#150000
b10 +
1"
#151000
b110 $
#160000
0"
#170000
b11 +
1"
#171000
b111 $
#180000
0"
#190000
0!
b0 +
1"
