lab2/lab2_04_shift_register/src/shift_register4.v
`timescale 1ns/1ps
// Serial input enters bit 3 and moves toward bit 0.
module shift_register4 (
    input wire clk, rst, enable, serial_in,
    output reg [3:0] value
);

    always @(posedge clk) begin
        if (rst) value <= 4'd0;
        else if (enable) value <= {serial_in, value[3:1]};
    end
endmodule

lab2/lab2_04_shift_register/evidence/normal/source/sim/tb_shift_register4.sv
`timescale 1ns/1ps
module tb_shift_register4;
    reg clk = 0, rst = 1;
    integer checks = 0;
    always #5 clk = ~clk;

    task step; begin @(posedge clk); #1; end endtask
    task check(input condition, input [8*100-1:0] description); begin
        checks = checks + 1;
        if (condition !== 1'b1) begin
            $display("LAB2_FAIL %0s time=%0t", description, $time);
            $fatal(1, "check failed");
        end
    end endtask
    task finish; begin
        $display("LAB2_PASS shift_register4 checks=%0d", checks);
        $finish;
    end endtask

    initial begin $dumpfile("wave.vcd"); $dumpvars(0, tb_shift_register4); end
    initial begin #1000; $fatal(1, "watchdog timeout"); end

    reg enable = 0, serial_in = 0;
    wire [3:0] value;
    shift_register4 dut(clk, rst, enable, serial_in, value);

    initial begin
        step; check(value === 0, "reset"); rst = 0; enable = 1;
        serial_in = 1; step; check(value === 4'b1000, "input enters MSB");
        serial_in = 0; step; check(value === 4'b0100, "move toward LSB");
        enable = 0; serial_in = 1; step; check(value === 4'b0100, "hold");
        enable = 1; step; check(value === 4'b1010, "retain old stage values");
        serial_in = 0; step; check(value === 4'b0101, "four bit history");
        repeat (4) step; check(value === 0, "flush with four zeros");
        serial_in = 1; rst = 1; step; check(value === 0, "reset priority");
        finish;
    end
endmodule

lab2/lab2_04_shift_register/evidence/normal/wave.vcd
$date
	Sun Sep 20 23:51:55 2026
$end
$version
	Icarus Verilog
$end
$timescale
	1ps
$end
$scope module tb_shift_register4 $end
$var wire 4 ! value [3:0] $end
$var reg 1 " clk $end
$var reg 1 # enable $end
$var reg 1 $ rst $end
$var reg 1 % serial_in $end
$var integer 32 & checks [31:0] $end
$scope module dut $end
$var wire 1 " clk $end
$var wire 1 # enable $end
$var wire 1 $ rst $end
$var wire 1 % serial_in $end
$var reg 4 ' value [3:0] $end
$upscope $end
$scope task check $end
$var reg 1 ( condition $end
$var reg 800 ) description [799:0] $end
$upscope $end
$scope task finish $end
$upscope $end
$scope task step $end
$upscope $end
$upscope $end
$enddefinitions $end
$comment Show the parameter values. $end
$dumpall
$end
#0
$dumpvars
bx )
x(
bx '
b0 &
0%
1$
0#
0"
bx !
$end
#5000
b0 !
b0 '
1"
#6000
1%
1#
0$
b1 &
b111001001100101011100110110010101110100 )
1(
#10000
0"
#15000
b1000 !
b1000 '
1"
#16000
0%
b10 &
b1101001011011100111000001110101011101000010000001100101011011100111010001100101011100100111001100100000010011010101001101000010 )
#20000
0"
#25000
b100 !
b100 '
1"
#26000
1%
0#
b11 &
b11011010110111101110110011001010010000001110100011011110111011101100001011100100110010000100000010011000101001101000010 )
#30000
0"
#35000
1"
#36000
1#
b100 &
b1101000011011110110110001100100 )
#40000
0"
#45000
b1010 !
b1010 '
1"
#46000
0%
b101 &
b111001001100101011101000110000101101001011011100010000001101111011011000110010000100000011100110111010001100001011001110110010100100000011101100110000101101100011101010110010101110011 )
#50000
0"
#55000
b101 !
b101 '
1"
#56000
b110 &
b1100110011011110111010101110010001000000110001001101001011101000010000001101000011010010111001101110100011011110111001001111001 )
#60000
0"
#65000
b10 !
b10 '
1"
#70000
0"
#75000
b1 !
b1 '
1"
#80000
0"
#85000
b0 !
b0 '
1"
#90000
0"
#95000
1"
#96000
1$
1%
b111 &
b11001100110110001110101011100110110100000100000011101110110100101110100011010000010000001100110011011110111010101110010001000000111101001100101011100100110111101110011 )
#100000
0"
#105000
1"
#106000
b1000 &
b111001001100101011100110110010101110100001000000111000001110010011010010110111101110010011010010111010001111001 )
