lab1/lab1_09_decoder3to8/src/decoder3x8.v
module decoder3x8(input wire a,b,c, output wire [7:0] o);
    assign o = 8'b00000001 << {a,b,c};
endmodule

lab1/lab1_09_decoder3to8/sim/tb_decoder3x8.sv
`timescale 1ns/1ps
module tb_decoder3x8;
  reg a,b,c; wire [7:0] o; decoder3x8 dut(a,b,c,o);
  integer n,checked=0;
  reg [7:0] expected;
  initial begin
    $dumpfile("wave.vcd"); $dumpvars(0,tb_decoder3x8);
    for(n=0;n<8;n=n+1) begin
      {a,b,c}=n;
      expected=1 << n;
      #10;
      if (o !== expected) begin
        $fatal(1,"FAIL decoder3x8 vector=%0d expected=%h actual=%h",n,expected,o);
      end
      checked=checked+1;
    end
    if(checked!=8) $fatal(1,"Incomplete test");
    $display("LAB1_PASS decoder3x8 cases=%0d",checked);
    $finish;
  end
  initial begin #100000; $fatal(1,"Watchdog"); end
endmodule

lab1/lab1_09_decoder3to8/evidence/vscode/wave.vcd
$date
	Mon Sep 14 12:17:01 2026
$end
$version
	Icarus Verilog
$end
$timescale
	1ps
$end
$scope module tb_decoder3x8 $end
$var wire 8 ! o [7:0] $end
$var reg 1 " a $end
$var reg 1 # b $end
$var reg 1 $ c $end
$var reg 8 % expected [7:0] $end
$var integer 32 & checked [31:0] $end
$var integer 32 ' n [31:0] $end
$scope module dut $end
$var wire 1 " a $end
$var wire 1 # b $end
$var wire 1 $ c $end
$var wire 8 ( o [7:0] $end
$upscope $end
$upscope $end
$enddefinitions $end
$comment Show the parameter values. $end
$dumpall
$end
#0
$dumpvars
b1 (
b0 '
b0 &
b1 %
0$
0#
0"
b1 !
$end
#10000
b10 !
b10 (
b10 %
1$
b1 '
b1 &
#20000
b100 !
b100 (
b100 %
1#
0$
b10 '
b10 &
#30000
b1000 !
b1000 (
b1000 %
1$
b11 '
b11 &
#40000
b10000 !
b10000 (
b10000 %
1"
0#
0$
b100 '
b100 &
#50000
b100000 !
b100000 (
b100000 %
1$
b101 '
b101 &
#60000
b1000000 !
b1000000 (
b1000000 %
1#
0$
b110 '
b110 &
#70000
b10000000 !
b10000000 (
b10000000 %
1$
b111 '
b111 &
#80000
b1000 '
b1000 &
